Workbook
Name AnnualRate: #REF!
Name bnc_10000: Taux!$D$7
Name bnc_15000: Taux!$D$8
Name bnc_5000: Taux!$D$5
Name bnc_7500: Taux!$D$6
Name Fairstone36mois: Taux!#REF!
Name Fairstone48mois: Taux!#REF!
Name Fairstone60mois: Taux!#REF!
Name FinanceIt: Taux!$F$4
Name MontantFinancement: Calculatrice!$B$11
Name Months: #REF!

Sheet 2025-05-01
D6: PAIEMENT | K6: PAIEMENT | Q6: Plan 36369 | W6: Plan 36485 | AD6: Plan 36602 | AK6: Plan 18363 (36 mois) et 18483 (48 mois) | AR6: TERME | AX6: TERME
D7: MENSUEL | E7: 2 SEMAINES | F7: 1 SEMAINE | K7: MENSUEL | L7: 2 SEMAINES | M7: 1 SEMAINE | Q7: 36 | S7: 36 | W7: 48 | Y7: 48 | AD7: 60 | AF7: 60 | AK7: 36 | AL7: 48 | AN7: 36 | AO7: 48 | AR7: 180 | AT7: 180 | AX7: 240 | AZ7: 240
A8: FIXE | B8: 120 MOIS @ 11.39% | C8: 5000 | D8: =PMT(bnc_5000/12, 120, -C8) -> 69.983428 | E8: =PMT(bnc_5000/26, 120/12*26, -C8) -> 32.255955 | F8: =PMT(bnc_5000/52, 120/12*52, -C8) -> 16.118522 | H8: FIXE | I8: 120 MOIS @ 10.89% | J8: 10250 | K8: =PMT(bnc_10000/12, 120, -J8) -> 140.55629 | L8: =PMT(bnc_10000/26, 120/12*26, -J8) -> 64.784929 | M8: =PMT(bnc_10000/52, 120/12*52, -J8) -> 32.373762 | O8: 0.0499 | P8: 250 | Q8: =PMT(0.0499/12, 36, -P8) -> 7.4916019 | R8: 7500 | S8: =PMT(0.0499/12, 36, -R8) -> 224.74806 | U8: 0.0599 | V8: 250 | W8: =PMT(0.0599/12, 48, -V8) -> 5.8701111 | X8: 7500 | Y8: =PMT(0.0599/12, 48, -X8) -> 176.10333 | AB8: 0.0899 | AC8: 250 | AD8: =PMT(0.0899/12, 60, -AC8) -> 5.1883756 | AE8: 7500 | AF8: =PMT(0.0899/12, 60, -AE8) -> 155.65127 | AI8: 0.1099 | AJ8: 250 | AK8: =PMT(0.1099/12, 36, -AJ8) -> 8.1834954 | AL8: =PMT(0.1099/12, 48, -AJ8) -> 6.4601666 | AM8: 7500 | AN8: =PMT(0.1099/12, 36, -AM8) -> 245.50486 | AO8: =PMT(0.1099/12, 48, -AM8) -> 193.805 | AP8: 0.1299 | AQ8: 250 | AR8: =PMT(FinanceIt/12, 180, -AQ8) -> 3.1614606 | AS8: =AQ36+250 -> 7500 | AT8: =PMT(FinanceIt/12, 180, -AS8) -> 94.843818 | AV8: 0.1299 | AW8: 10000 | AX8: =PMT(FinanceIt/12, 240, -AW8) -> 117.08634 | AY8: =AW36+250 -> 17250 | AZ8: =PMT(FinanceIt/12, 240, -AY8) -> 201.97393
C9: =C8+250 -> 5250 | D9: =PMT(bnc_5000/12, 120, -C9) -> 73.4826 | E9: =PMT(bnc_5000/26, 120/12*26, -C9) -> 33.868753 | F9: =PMT(bnc_5000/52, 120/12*52, -C9) -> 16.924448 | J9: =J8+250 -> 10500 | K9: =PMT(bnc_10000/12, 120, -J9) -> 143.98449 | L9: =PMT(bnc_10000/26, 120/12*26, -J9) -> 66.365049 | M9: =PMT(bnc_10000/52, 120/12*52, -J9) -> 33.163366 | P9: =P8+250 -> 500 | Q9: =PMT(0.0499/12, 36, -P9) -> 14.983204 | R9: =R8+250 -> 7750 | S9: =PMT(0.0499/12, 36, -R9) -> 232.23966 | V9: =V8+250 -> 500 | W9: =PMT(0.0599/12, 48, -V9) -> 11.740222 | X9: =X8+250 -> 7750 | Y9: =PMT(0.0599/12, 48, -X9) -> 181.97345 | AC9: =AC8+250 -> 500 | AD9: =PMT(0.0899/12, 60, -AC9) -> 10.376751 | AE9: =AE8+250 -> 7750 | AF9: =PMT(0.0899/12, 60, -AE9) -> 160.83964 | AJ9: =AJ8+250 -> 500 | AK9: =PMT(0.1099/12, 36, -AJ9) -> 16.366991 | AL9: =PMT(0.1099/12, 48, -AJ9) -> 12.920333 | AM9: =AM8+250 -> 7750 | AN9: =PMT(0.1099/12, 36, -AM9) -> 253.68836 | AO9: =PMT(0.1099/12, 48, -AM9) -> 200.26517 | AQ9: =AQ8+250 -> 500 | AR9: =PMT(FinanceIt/12, 180, -AQ9) -> 6.3229212 | AS9: =AS8+250 -> 7750 | AT9: =PMT(FinanceIt/12, 180, -AS9) -> 98.005279 | AW9: =AW8+250 -> 10250 | AX9: =PMT(FinanceIt/12, 240, -AW9) -> 120.0135 | AY9: =AY8+250 -> 17500 | AZ9: =PMT(FinanceIt/12, 240, -AY9) -> 204.90109
C10: =C9+250 -> 5500 | D10: =PMT(bnc_5000/12, 120, -C10) -> 76.981771 | E10: =PMT(bnc_5000/26, 120/12*26, -C10) -> 35.481551 | F10: =PMT(bnc_5000/52, 120/12*52, -C10) -> 17.730374 | J10: =J9+250 -> 10750 | K10: =PMT(bnc_10000/12, 120, -J10) -> 147.41269 | L10: =PMT(bnc_10000/26, 120/12*26, -J10) -> 67.945169 | M10: =PMT(bnc_10000/52, 120/12*52, -J10) -> 33.95297 | P10: =P9+250 -> 750 | Q10: =PMT(0.0499/12, 36, -P10) -> 22.474806 | R10: =R9+250 -> 8000 | S10: =PMT(0.0499/12, 36, -R10) -> 239.73126 | V10: =V9+250 -> 750 | W10: =PMT(0.0599/12, 48, -V10) -> 17.610333 | X10: =X9+250 -> 8000 | Y10: =PMT(0.0599/12, 48, -X10) -> 187.84356 | AC10: =AC9+250 -> 750 | AD10: =PMT(0.0899/12, 60, -AC10) -> 15.565127 | AE10: =AE9+250 -> 8000 | AF10: =PMT(0.0899/12, 60, -AE10) -> 166.02802 | AJ10: =AJ9+250 -> 750 | AK10: =PMT(0.1099/12, 36, -AJ10) -> 24.550486 | AL10: =PMT(0.1099/12, 48, -AJ10) -> 19.3805 | AM10: =AM9+250 -> 8000 | AN10: =PMT(0.1099/12, 36, -AM10) -> 261.87185 | AO10: =PMT(0.1099/12, 48, -AM10) -> 206.72533 | AQ10: =AQ9+250 -> 750 | AR10: =PMT(FinanceIt/12, 180, -AQ10) -> 9.4843818 | AS10: =AS9+250 -> 8000 | AT10: =PMT(FinanceIt/12, 180, -AS10) -> 101.16674 | AW10: =AW9+250 -> 10500 | AX10: =PMT(FinanceIt/12, 240, -AW10) -> 122.94066 | AY10: =AY9+250 -> 17750 | AZ10: =PMT(FinanceIt/12, 240, -AY10) -> 207.82825
C11: =C10+250 -> 5750 | D11: =PMT(bnc_5000/12, 120, -C11) -> 80.480942 | E11: =PMT(bnc_5000/26, 120/12*26, -C11) -> 37.094348 | F11: =PMT(bnc_5000/52, 120/12*52, -C11) -> 18.536301 | J11: =J10+250 -> 11000 | K11: =PMT(bnc_10000/12, 120, -J11) -> 150.84089 | L11: =PMT(bnc_10000/26, 120/12*26, -J11) -> 69.525289 | M11: =PMT(bnc_10000/52, 120/12*52, -J11) -> 34.742574 | P11: =P10+250 -> 1000 | Q11: =PMT(0.0499/12, 36, -P11) -> 29.966408 | R11: =R10+250 -> 8250 | S11: =PMT(0.0499/12, 36, -R11) -> 247.22286 | V11: =V10+250 -> 1000 | W11: =PMT(0.0599/12, 48, -V11) -> 23.480445 | X11: =X10+250 -> 8250 | Y11: =PMT(0.0599/12, 48, -X11) -> 193.71367 | AC11: =AC10+250 -> 1000 | AD11: =PMT(0.0899/12, 60, -AC11) -> 20.753502 | AE11: =AE10+250 -> 8250 | AF11: =PMT(0.0899/12, 60, -AE11) -> 171.21639 | AJ11: =AJ10+250 -> 1000 | AK11: =PMT(0.1099/12, 36, -AJ11) -> 32.733982 | AL11: =PMT(0.1099/12, 48, -AJ11) -> 25.840667 | AM11: =AM10+250 -> 8250 | AN11: =PMT(0.1099/12, 36, -AM11) -> 270.05535 | AO11: =PMT(0.1099/12, 48, -AM11) -> 213.1855 | AQ11: =AQ10+250 -> 1000 | AR11: =PMT(FinanceIt/12, 180, -AQ11) -> 12.645842 | AS11: =AS10+250 -> 8250 | AT11: =PMT(FinanceIt/12, 180, -AS11) -> 104.3282 | AW11: =AW10+250 -> 10750 | AX11: =PMT(FinanceIt/12, 240, -AW11) -> 125.86781 | AY11: =AY10+250 -> 18000 | AZ11: =PMT(FinanceIt/12, 240, -AY11) -> 210.75541
C12: =C11+250 -> 6000 | D12: =PMT(bnc_5000/12, 120, -C12) -> 83.980114 | E12: =PMT(bnc_5000/26, 120/12*26, -C12) -> 38.707146 | F12: =PMT(bnc_5000/52, 120/12*52, -C12) -> 19.342227 | J12: =J11+250 -> 11250 | K12: =PMT(bnc_10000/12, 120, -J12) -> 154.2691 | L12: =PMT(bnc_10000/26, 120/12*26, -J12) -> 71.105409 | M12: =PMT(bnc_10000/52, 120/12*52, -J12) -> 35.532178 | P12: =P11+250 -> 1250 | Q12: =PMT(0.0499/12, 36, -P12) -> 37.458009 | R12: =R11+250 -> 8500 | S12: =PMT(0.0499/12, 36, -R12) -> 254.71446 | V12: =V11+250 -> 1250 | W12: =PMT(0.0599/12, 48, -V12) -> 29.350556 | X12: =X11+250 -> 8500 | Y12: =PMT(0.0599/12, 48, -X12) -> 199.58378 | AC12: =AC11+250 -> 1250 | AD12: =PMT(0.0899/12, 60, -AC12) -> 25.941878 | AE12: =AE11+250 -> 8500 | AF12: =PMT(0.0899/12, 60, -AE12) -> 176.40477 | AJ12: =AJ11+250 -> 1250 | AK12: =PMT(0.1099/12, 36, -AJ12) -> 40.917477 | AL12: =PMT(0.1099/12, 48, -AJ12) -> 32.300833 | AM12: =AM11+250 -> 8500 | AN12: =PMT(0.1099/12, 36, -AM12) -> 278.23884 | AO12: =PMT(0.1099/12, 48, -AM12) -> 219.64567 | AQ12: =AQ11+250 -> 1250 | AR12: =PMT(FinanceIt/12, 180, -AQ12) -> 15.807303 | AS12: =AS11+250 -> 8500 | AT12: =PMT(FinanceIt/12, 180, -AS12) -> 107.48966 | AW12: =AW11+250 -> 11000 | AX12: =PMT(FinanceIt/12, 240, -AW12) -> 128.79497 | AY12: =AY11+250 -> 18250 | AZ12: =PMT(FinanceIt/12, 240, -AY12) -> 213.68257
C13: =C12+250 -> 6250 | D13: =PMT(bnc_5000/12, 120, -C13) -> 87.479285 | E13: =PMT(bnc_5000/26, 120/12*26, -C13) -> 40.319944 | F13: =PMT(bnc_5000/52, 120/12*52, -C13) -> 20.148153 | J13: =J12+250 -> 11500 | K13: =PMT(bnc_10000/12, 120, -J13) -> 157.6973 | L13: =PMT(bnc_10000/26, 120/12*26, -J13) -> 72.68553 | M13: =PMT(bnc_10000/52, 120/12*52, -J13) -> 36.321782 | P13: =P12+250 -> 1500 | Q13: =PMT(0.0499/12, 36, -P13) -> 44.949611 | R13: =R12+250 -> 8750 | S13: =PMT(0.0499/12, 36, -R13) -> 262.20607 | V13: =V12+250 -> 1500 | W13: =PMT(0.0599/12, 48, -V13) -> 35.220667 | X13: =X12+250 -> 8750 | Y13: =PMT(0.0599/12, 48, -X13) -> 205.45389 | AC13: =AC12+250 -> 1500 | AD13: =PMT(0.0899/12, 60, -AC13) -> 31.130253 | AE13: =AE12+250 -> 8750 | AF13: =PMT(0.0899/12, 60, -AE13) -> 181.59314 | AJ13: =AJ12+250 -> 1500 | AK13: =PMT(0.1099/12, 36, -AJ13) -> 49.100973 | AL13: =PMT(0.1099/12, 48, -AJ13) -> 38.761 | AM13: =AM12+250 -> 8750 | AN13: =PMT(0.1099/12, 36, -AM13) -> 286.42234 | AO13: =PMT(0.1099/12, 48, -AM13) -> 226.10583 | AQ13: =AQ12+250 -> 1500 | AR13: =PMT(FinanceIt/12, 180, -AQ13) -> 18.968764 | AS13: =AS12+250 -> 8750 | AT13: =PMT(FinanceIt/12, 180, -AS13) -> 110.65112 | AW13: =AW12+250 -> 11250 | AX13: =PMT(FinanceIt/12, 240, -AW13) -> 131.72213 | AY13: =AY12+250 -> 18500 | AZ13: =PMT(FinanceIt/12, 240, -AY13) -> 216.60973
C14: =C13+250 -> 6500 | D14: =PMT(bnc_5000/12, 120, -C14) -> 90.978457 | E14: =PMT(bnc_5000/26, 120/12*26, -C14) -> 41.932742 | F14: =PMT(bnc_5000/52, 120/12*52, -C14) -> 20.954079 | J14: =J13+250 -> 11750 | K14: =PMT(bnc_10000/12, 120, -J14) -> 161.1255 | L14: =PMT(bnc_10000/26, 120/12*26, -J14) -> 74.26565 | M14: =PMT(bnc_10000/52, 120/12*52, -J14) -> 37.111386 | P14: =P13+250 -> 1750 | Q14: =PMT(0.0499/12, 36, -P14) -> 52.441213 | R14: =R13+250 -> 9000 | S14: =PMT(0.0499/12, 36, -R14) -> 269.69767 | V14: =V13+250 -> 1750 | W14: =PMT(0.0599/12, 48, -V14) -> 41.090778 | X14: =X13+250 -> 9000 | Y14: =PMT(0.0599/12, 48, -X14) -> 211.324 | AC14: =AC13+250 -> 1750 | AD14: =PMT(0.0899/12, 60, -AC14) -> 36.318629 | AE14: =AE13+250 -> 9000 | AF14: =PMT(0.0899/12, 60, -AE14) -> 186.78152 | AJ14: =AJ13+250 -> 1750 | AK14: =PMT(0.1099/12, 36, -AJ14) -> 57.284468 | AL14: =PMT(0.1099/12, 48, -AJ14) -> 45.221167 | AM14: =AM13+250 -> 9000 | AN14: =PMT(0.1099/12, 36, -AM14) -> 294.60584 | AO14: =PMT(0.1099/12, 48, -AM14) -> 232.566 | AQ14: =AQ13+250 -> 1750 | AR14: =PMT(FinanceIt/12, 180, -AQ14) -> 22.130224 | AS14: =AS13+250 -> 9000 | AT14: =PMT(FinanceIt/12, 180, -AS14) -> 113.81258 | AW14: =AW13+250 -> 11500 | AX14: =PMT(FinanceIt/12, 240, -AW14) -> 134.64929 | AY14: =AY13+250 -> 18750 | AZ14: =PMT(FinanceIt/12, 240, -AY14) -> 219.53689
C15: =C14+250 -> 6750 | D15: =PMT(bnc_5000/12, 120, -C15) -> 94.477628 | E15: =PMT(bnc_5000/26, 120/12*26, -C15) -> 43.545539 | F15: =PMT(bnc_5000/52, 120/12*52, -C15) -> 21.760005 | J15: =J14+250 -> 12000 | K15: =PMT(bnc_10000/12, 120, -J15) -> 164.5537 | L15: =PMT(bnc_10000/26, 120/12*26, -J15) -> 75.84577 | M15: =PMT(bnc_10000/52, 120/12*52, -J15) -> 37.90099 | P15: =P14+250 -> 2000 | Q15: =PMT(0.0499/12, 36, -P15) -> 59.932815 | R15: =R14+250 -> 9250 | S15: =PMT(0.0499/12, 36, -R15) -> 277.18927 | V15: =V14+250 -> 2000 | W15: =PMT(0.0599/12, 48, -V15) -> 46.960889 | X15: =X14+250 -> 9250 | Y15: =PMT(0.0599/12, 48, -X15) -> 217.19411 | AC15: =AC14+250 -> 2000 | AD15: =PMT(0.0899/12, 60, -AC15) -> 41.507004 | AE15: =AE14+250 -> 9250 | AF15: =PMT(0.0899/12, 60, -AE15) -> 191.9699 | AJ15: =AJ14+250 -> 2000 | AK15: =PMT(0.1099/12, 36, -AJ15) -> 65.467963 | AL15: =PMT(0.1099/12, 48, -AJ15) -> 51.681333 | AM15: =AM14+250 -> 9250 | AN15: =PMT(0.1099/12, 36, -AM15) -> 302.78933 | AO15: =PMT(0.1099/12, 48, -AM15) -> 239.02617 | AQ15: =AQ14+250 -> 2000 | AR15: =PMT(FinanceIt/12, 180, -AQ15) -> 25.291685 | AS15: =AS14+250 -> 9250 | AT15: =PMT(FinanceIt/12, 180, -AS15) -> 116.97404 | AW15: =AW14+250 -> 11750 | AX15: =PMT(FinanceIt/12, 240, -AW15) -> 137.57645 | AY15: =AY14+250 -> 19000 | AZ15: =PMT(FinanceIt/12, 240, -AY15) -> 222.46404
C16: =C15+250 -> 7000 | D16: =PMT(bnc_5000/12, 120, -C16) -> 97.976799 | E16: =PMT(bnc_5000/26, 120/12*26, -C16) -> 45.158337 | F16: =PMT(bnc_5000/52, 120/12*52, -C16) -> 22.565931 | J16: =J15+250 -> 12250 | K16: =PMT(bnc_10000/12, 120, -J16) -> 167.98191 | L16: =PMT(bnc_10000/26, 120/12*26, -J16) -> 77.42589 | M16: =PMT(bnc_10000/52, 120/12*52, -J16) -> 38.690594 | P16: =P15+250 -> 2250 | Q16: =PMT(0.0499/12, 36, -P16) -> 67.424417 | R16: =R15+250 -> 9500 | S16: =PMT(0.0499/12, 36, -R16) -> 284.68087 | V16: =V15+250 -> 2250 | W16: =PMT(0.0599/12, 48, -V16) -> 52.831 | X16: =X15+250 -> 9500 | Y16: =PMT(0.0599/12, 48, -X16) -> 223.06422 | AC16: =AC15+250 -> 2250 | AD16: =PMT(0.0899/12, 60, -AC16) -> 46.69538 | AE16: =AE15+250 -> 9500 | AF16: =PMT(0.0899/12, 60, -AE16) -> 197.15827 | AJ16: =AJ15+250 -> 2250 | AK16: =PMT(0.1099/12, 36, -AJ16) -> 73.651459 | AL16: =PMT(0.1099/12, 48, -AJ16) -> 58.1415 | AM16: =AM15+250 -> 9500 | AN16: =PMT(0.1099/12, 36, -AM16) -> 310.97283 | AO16: =PMT(0.1099/12, 48, -AM16) -> 245.48633 | AQ16: =AQ15+250 -> 2250 | AR16: =PMT(FinanceIt/12, 180, -AQ16) -> 28.453145 | AS16: =AS15+250 -> 9500 | AT16: =PMT(FinanceIt/12, 180, -AS16) -> 120.1355 | AW16: =AW15+250 -> 12000 | AX16: =PMT(FinanceIt/12, 240, -AW16) -> 140.50361 | AY16: =AY15+250 -> 19250 | AZ16: =PMT(FinanceIt/12, 240, -AY16) -> 225.3912
C17: =C16+250 -> 7250 | D17: =PMT(bnc_5000/12, 120, -C17) -> 101.47597 | E17: =PMT(bnc_5000/26, 120/12*26, -C17) -> 46.771135 | F17: =PMT(bnc_5000/52, 120/12*52, -C17) -> 23.371857 | J17: =J16+250 -> 12500 | K17: =PMT(bnc_10000/12, 120, -J17) -> 171.41011 | L17: =PMT(bnc_10000/26, 120/12*26, -J17) -> 79.00601 | M17: =PMT(bnc_10000/52, 120/12*52, -J17) -> 39.480198 | P17: =P16+250 -> 2500 | Q17: =PMT(0.0499/12, 36, -P17) -> 74.916019 | R17: =R16+250 -> 9750 | S17: =PMT(0.0499/12, 36, -R17) -> 292.17247 | V17: =V16+250 -> 2500 | W17: =PMT(0.0599/12, 48, -V17) -> 58.701111 | X17: =X16+250 -> 9750 | Y17: =PMT(0.0599/12, 48, -X17) -> 228.93433 | AC17: =AC16+250 -> 2500 | AD17: =PMT(0.0899/12, 60, -AC17) -> 51.883756 | AE17: =AE16+250 -> 9750 | AF17: =PMT(0.0899/12, 60, -AE17) -> 202.34665 | AJ17: =AJ16+250 -> 2500 | AK17: =PMT(0.1099/12, 36, -AJ17) -> 81.834954 | AL17: =PMT(0.1099/12, 48, -AJ17) -> 64.601666 | AM17: =AM16+250 -> 9750 | AN17: =PMT(0.1099/12, 36, -AM17) -> 319.15632 | AO17: =PMT(0.1099/12, 48, -AM17) -> 251.9465 | AQ17: =AQ16+250 -> 2500 | AR17: =PMT(FinanceIt/12, 180, -AQ17) -> 31.614606 | AS17: =AS16+250 -> 9750 | AT17: =PMT(FinanceIt/12, 180, -AS17) -> 123.29696 | AW17: =AW16+250 -> 12250 | AX17: =PMT(FinanceIt/12, 240, -AW17) -> 143.43076 | AY17: =AY16+250 -> 19500 | AZ17: =PMT(FinanceIt/12, 240, -AY17) -> 228.31836
C18: =C17+250 -> 7500 | D18: =PMT(bnc_5000/12, 120, -C18) -> 104.97514 | E18: =PMT(bnc_5000/26, 120/12*26, -C18) -> 48.383933 | F18: =PMT(bnc_5000/52, 120/12*52, -C18) -> 24.177783 | J18: =J17+250 -> 12750 | K18: =PMT(bnc_10000/12, 120, -J18) -> 174.83831 | L18: =PMT(bnc_10000/26, 120/12*26, -J18) -> 80.586131 | M18: =PMT(bnc_10000/52, 120/12*52, -J18) -> 40.269802 | P18: =P17+250 -> 2750 | Q18: =PMT(0.0499/12, 36, -P18) -> 82.407621 | R18: =R17+250 -> 10000 | S18: =PMT(0.0499/12, 36, -R18) -> 299.66408 | V18: =V17+250 -> 2750 | W18: =PMT(0.0599/12, 48, -V18) -> 64.571222 | X18: =X17+250 -> 10000 | Y18: =PMT(0.0599/12, 48, -X18) -> 234.80445 | AC18: =AC17+250 -> 2750 | AD18: =PMT(0.0899/12, 60, -AC18) -> 57.072131 | AE18: =AE17+250 -> 10000 | AF18: =PMT(0.0899/12, 60, -AE18) -> 207.53502 | AJ18: =AJ17+250 -> 2750 | AK18: =PMT(0.1099/12, 36, -AJ18) -> 90.01845 | AL18: =PMT(0.1099/12, 48, -AJ18) -> 71.061833 | AM18: =AM17+250 -> 10000 | AN18: =PMT(0.1099/12, 36, -AM18) -> 327.33982 | AO18: =PMT(0.1099/12, 48, -AM18) -> 258.40667 | AQ18: =AQ17+250 -> 2750 | AR18: =PMT(FinanceIt/12, 180, -AQ18) -> 34.776067 | AS18: =AS17+250 -> 10000 | AT18: =PMT(FinanceIt/12, 180, -AS18) -> 126.45842 | AW18: =AW17+250 -> 12500 | AX18: =PMT(FinanceIt/12, 240, -AW18) -> 146.35792 | AY18: =AY17+250 -> 19750 | AZ18: =PMT(FinanceIt/12, 240, -AY18) -> 231.24552
B19: 120 MOIS @ 10.89% | C19: =C18+250 -> 7750 | D19: =PMT(bnc_7500/12, 120, -C19) -> 106.27427 | E19: =PMT(bnc_7500/26, 120/12*26, -C19) -> 48.983726 | F19: =PMT(bnc_7500/52, 120/12*52, -C19) -> 24.477723 | J19: =J18+250 -> 13000 | K19: =PMT(bnc_10000/12, 120, -J19) -> 178.26651 | L19: =PMT(bnc_10000/26, 120/12*26, -J19) -> 82.166251 | M19: =PMT(bnc_10000/52, 120/12*52, -J19) -> 41.059406 | P19: =P18+250 -> 3000 | Q19: =PMT(0.0499/12, 36, -P19) -> 89.899223 | R19: =R18+250 -> 10250 | S19: =PMT(0.0499/12, 36, -R19) -> 307.15568 | V19: =V18+250 -> 3000 | W19: =PMT(0.0599/12, 48, -V19) -> 70.441334 | X19: =X18+250 -> 10250 | Y19: =PMT(0.0599/12, 48, -X19) -> 240.67456 | AC19: =AC18+250 -> 3000 | AD19: =PMT(0.0899/12, 60, -AC19) -> 62.260507 | AE19: =AE18+250 -> 10250 | AF19: =PMT(0.0899/12, 60, -AE19) -> 212.7234 | AJ19: =AJ18+250 -> 3000 | AK19: =PMT(0.1099/12, 36, -AJ19) -> 98.201945 | AL19: =PMT(0.1099/12, 48, -AJ19) -> 77.522 | AM19: =AM18+250 -> 10250 | AN19: =PMT(0.1099/12, 36, -AM19) -> 335.52331 | AO19: =PMT(0.1099/12, 48, -AM19) -> 264.86683 | AQ19: =AQ18+250 -> 3000 | AR19: =PMT(FinanceIt/12, 180, -AQ19) -> 37.937527 | AW19: =AW18+250 -> 12750 | AX19: =PMT(FinanceIt/12, 240, -AW19) -> 149.28508 | AY19: =AY18+250 -> 20000 | AZ19: =PMT(FinanceIt/12, 240, -AY19) -> 234.17268
C20: =C19+250 -> 8000 | D20: =PMT(bnc_7500/12, 120, -C20) -> 109.70247 | E20: =PMT(bnc_7500/26, 120/12*26, -C20) -> 50.563847 | F20: =PMT(bnc_7500/52, 120/12*52, -C20) -> 25.267327 | J20: =J19+250 -> 13250 | K20: =PMT(bnc_10000/12, 120, -J20) -> 181.69471 | L20: =PMT(bnc_10000/26, 120/12*26, -J20) -> 83.746371 | M20: =PMT(bnc_10000/52, 120/12*52, -J20) -> 41.84901 | P20: =P19+250 -> 3250 | Q20: =PMT(0.0499/12, 36, -P20) -> 97.390824 | R20: =R19+250 -> 10500 | S20: =PMT(0.0499/12, 36, -R20) -> 314.64728 | V20: =V19+250 -> 3250 | W20: =PMT(0.0599/12, 48, -V20) -> 76.311445 | X20: =X19+250 -> 10500 | Y20: =PMT(0.0599/12, 48, -X20) -> 246.54467 | AC20: =AC19+250 -> 3250 | AD20: =PMT(0.0899/12, 60, -AC20) -> 67.448882 | AE20: =AE19+250 -> 10500 | AF20: =PMT(0.0899/12, 60, -AE20) -> 217.91177 | AJ20: =AJ19+250 -> 3250 | AK20: =PMT(0.1099/12, 36, -AJ20) -> 106.38544 | AL20: =PMT(0.1099/12, 48, -AJ20) -> 83.982166 | AM20: =AM19+250 -> 10500 | AN20: =PMT(0.1099/12, 36, -AM20) -> 343.70681 | AO20: =PMT(0.1099/12, 48, -AM20) -> 271.327 | AQ20: =AQ19+250 -> 3250 | AR20: =PMT(FinanceIt/12, 180, -AQ20) -> 41.098988 | AW20: =AW19+250 -> 13000 | AX20: =PMT(FinanceIt/12, 240, -AW20) -> 152.21224 | AY20: =AY19+250 -> 20250 | AZ20: =PMT(FinanceIt/12, 240, -AY20) -> 237.09984
C21: =C20+250 -> 8250 | D21: =PMT(bnc_7500/12, 120, -C21) -> 113.13067 | E21: =PMT(bnc_7500/26, 120/12*26, -C21) -> 52.143967 | F21: =PMT(bnc_7500/52, 120/12*52, -C21) -> 26.056931 | J21: =J20+250 -> 13500 | K21: =PMT(bnc_10000/12, 120, -J21) -> 185.12292 | L21: =PMT(bnc_10000/26, 120/12*26, -J21) -> 85.326491 | M21: =PMT(bnc_10000/52, 120/12*52, -J21) -> 42.638614 | P21: =P20+250 -> 3500 | Q21: =PMT(0.0499/12, 36, -P21) -> 104.88243 | R21: =R20+250 -> 10750 | S21: =PMT(0.0499/12, 36, -R21) -> 322.13888 | V21: =V20+250 -> 3500 | W21: =PMT(0.0599/12, 48, -V21) -> 82.181556 | X21: =X20+250 -> 10750 | Y21: =PMT(0.0599/12, 48, -X21) -> 252.41478 | AC21: =AC20+250 -> 3500 | AD21: =PMT(0.0899/12, 60, -AC21) -> 72.637258 | AE21: =AE20+250 -> 10750 | AF21: =PMT(0.0899/12, 60, -AE21) -> 223.10015 | AJ21: =AJ20+250 -> 3500 | AK21: =PMT(0.1099/12, 36, -AJ21) -> 114.56894 | AL21: =PMT(0.1099/12, 48, -AJ21) -> 90.442333 | AM21: =AM20+250 -> 10750 | AN21: =PMT(0.1099/12, 36, -AM21) -> 351.8903 | AO21: =PMT(0.1099/12, 48, -AM21) -> 277.78717 | AQ21: =AQ20+250 -> 3500 | AR21: =PMT(FinanceIt/12, 180, -AQ21) -> 44.260448 | AW21: =AW20+250 -> 13250 | AX21: =PMT(FinanceIt/12, 240, -AW21) -> 155.1394 | AY21: =AY20+250 -> 20500 | AZ21: =PMT(FinanceIt/12, 240, -AY21) -> 240.02699
C22: =C21+250 -> 8500 | D22: =PMT(bnc_7500/12, 120, -C22) -> 116.55887 | E22: =PMT(bnc_7500/26, 120/12*26, -C22) -> 53.724087 | F22: =PMT(bnc_7500/52, 120/12*52, -C22) -> 26.846535 | J22: =J21+250 -> 13750 | K22: =PMT(bnc_10000/12, 120, -J22) -> 188.55112 | L22: =PMT(bnc_10000/26, 120/12*26, -J22) -> 86.906611 | M22: =PMT(bnc_10000/52, 120/12*52, -J22) -> 43.428218 | P22: =P21+250 -> 3750 | Q22: =PMT(0.0499/12, 36, -P22) -> 112.37403 | R22: =R21+250 -> 11000 | S22: =PMT(0.0499/12, 36, -R22) -> 329.63048 | V22: =V21+250 -> 3750 | W22: =PMT(0.0599/12, 48, -V22) -> 88.051667 | X22: =X21+250 -> 11000 | Y22: =PMT(0.0599/12, 48, -X22) -> 258.28489 | AC22: =AC21+250 -> 3750 | AD22: =PMT(0.0899/12, 60, -AC22) -> 77.825633 | AE22: =AE21+250 -> 11000 | AF22: =PMT(0.0899/12, 60, -AE22) -> 228.28852 | AJ22: =AJ21+250 -> 3750 | AK22: =PMT(0.1099/12, 36, -AJ22) -> 122.75243 | AL22: =PMT(0.1099/12, 48, -AJ22) -> 96.9025 | AM22: =AM21+250 -> 11000 | AN22: =PMT(0.1099/12, 36, -AM22) -> 360.0738 | AO22: =PMT(0.1099/12, 48, -AM22) -> 284.24733 | AQ22: =AQ21+250 -> 3750 | AR22: =PMT(FinanceIt/12, 180, -AQ22) -> 47.421909 | AW22: =AW21+250 -> 13500 | AX22: =PMT(FinanceIt/12, 240, -AW22) -> 158.06656 | AY22: =AY21+250 -> 20750 | AZ22: =PMT(FinanceIt/12, 240, -AY22) -> 242.95415
C23: =C22+250 -> 8750 | D23: =PMT(bnc_7500/12, 120, -C23) -> 119.98708 | E23: =PMT(bnc_7500/26, 120/12*26, -C23) -> 55.304207 | F23: =PMT(bnc_7500/52, 120/12*52, -C23) -> 27.636138 | J23: =J22+250 -> 14000 | K23: =PMT(bnc_10000/12, 120, -J23) -> 191.97932 | L23: =PMT(bnc_10000/26, 120/12*26, -J23) -> 88.486732 | M23: =PMT(bnc_10000/52, 120/12*52, -J23) -> 44.217822 | P23: =P22+250 -> 4000 | Q23: =PMT(0.0499/12, 36, -P23) -> 119.86563 | R23: =R22+250 -> 11250 | S23: =PMT(0.0499/12, 36, -R23) -> 337.12208 | V23: =V22+250 -> 4000 | W23: =PMT(0.0599/12, 48, -V23) -> 93.921778 | X23: =X22+250 -> 11250 | Y23: =PMT(0.0599/12, 48, -X23) -> 264.155 | AC23: =AC22+250 -> 4000 | AD23: =PMT(0.0899/12, 60, -AC23) -> 83.014009 | AE23: =AE22+250 -> 11250 | AF23: =PMT(0.0899/12, 60, -AE23) -> 233.4769 | AJ23: =AJ22+250 -> 4000 | AK23: =PMT(0.1099/12, 36, -AJ23) -> 130.93593 | AL23: =PMT(0.1099/12, 48, -AJ23) -> 103.36267 | AM23: =AM22+250 -> 11250 | AN23: =PMT(0.1099/12, 36, -AM23) -> 368.25729 | AO23: =PMT(0.1099/12, 48, -AM23) -> 290.7075 | AQ23: =AQ22+250 -> 4000 | AR23: =PMT(FinanceIt/12, 180, -AQ23) -> 50.58337 | AW23: =AW22+250 -> 13750 | AX23: =PMT(FinanceIt/12, 240, -AW23) -> 160.99372 | AY23: =AY22+250 -> 21000 | AZ23: =PMT(FinanceIt/12, 240, -AY23) -> 245.88131
C24: =C23+250 -> 9000 | D24: =PMT(bnc_7500/12, 120, -C24) -> 123.41528 | E24: =PMT(bnc_7500/26, 120/12*26, -C24) -> 56.884327 | F24: =PMT(bnc_7500/52, 120/12*52, -C24) -> 28.425742 | J24: =J23+250 -> 14250 | K24: =PMT(bnc_10000/12, 120, -J24) -> 195.40752 | L24: =PMT(bnc_10000/26, 120/12*26, -J24) -> 90.066852 | M24: =PMT(bnc_10000/52, 120/12*52, -J24) -> 45.007425 | P24: =P23+250 -> 4250 | Q24: =PMT(0.0499/12, 36, -P24) -> 127.35723 | R24: =R23+250 -> 11500 | S24: =PMT(0.0499/12, 36, -R24) -> 344.61369 | V24: =V23+250 -> 4250 | W24: =PMT(0.0599/12, 48, -V24) -> 99.791889 | X24: =X23+250 -> 11500 | Y24: =PMT(0.0599/12, 48, -X24) -> 270.02511 | AC24: =AC23+250 -> 4250 | AD24: =PMT(0.0899/12, 60, -AC24) -> 88.202385 | AE24: =AE23+250 -> 11500 | AF24: =PMT(0.0899/12, 60, -AE24) -> 238.66528 | AJ24: =AJ23+250 -> 4250 | AK24: =PMT(0.1099/12, 36, -AJ24) -> 139.11942 | AL24: =PMT(0.1099/12, 48, -AJ24) -> 109.82283 | AM24: =AM23+250 -> 11500 | AN24: =PMT(0.1099/12, 36, -AM24) -> 376.44079 | AO24: =PMT(0.1099/12, 48, -AM24) -> 297.16767 | AQ24: =AQ23+250 -> 4250 | AR24: =PMT(FinanceIt/12, 180, -AQ24) -> 53.74483 | AW24: =AW23+250 -> 14000 | AX24: =PMT(FinanceIt/12, 240, -AW24) -> 163.92087 | AY24: =AY23+250 -> 21250 | AZ24: =PMT(FinanceIt/12, 240, -AY24) -> 248.80847
C25: =C24+250 -> 9250 | D25: =PMT(bnc_7500/12, 120, -C25) -> 126.84348 | E25: =PMT(bnc_7500/26, 120/12*26, -C25) -> 58.464448 | F25: =PMT(bnc_7500/52, 120/12*52, -C25) -> 29.215346 | J25: =J24+250 -> 14500 | K25: =PMT(bnc_10000/12, 120, -J25) -> 198.83573 | L25: =PMT(bnc_10000/26, 120/12*26, -J25) -> 91.646972 | M25: =PMT(bnc_10000/52, 120/12*52, -J25) -> 45.797029 | P25: =P24+250 -> 4500 | Q25: =PMT(0.0499/12, 36, -P25) -> 134.84883 | R25: =R24+250 -> 11750 | S25: =PMT(0.0499/12, 36, -R25) -> 352.10529 | V25: =V24+250 -> 4500 | W25: =PMT(0.0599/12, 48, -V25) -> 105.662 | X25: =X24+250 -> 11750 | Y25: =PMT(0.0599/12, 48, -X25) -> 275.89522 | AC25: =AC24+250 -> 4500 | AD25: =PMT(0.0899/12, 60, -AC25) -> 93.39076 | AE25: =AE24+250 -> 11750 | AF25: =PMT(0.0899/12, 60, -AE25) -> 243.85365 | AJ25: =AJ24+250 -> 4500 | AK25: =PMT(0.1099/12, 36, -AJ25) -> 147.30292 | AL25: =PMT(0.1099/12, 48, -AJ25) -> 116.283 | AM25: =AM24+250 -> 11750 | AN25: =PMT(0.1099/12, 36, -AM25) -> 384.62428 | AO25: =PMT(0.1099/12, 48, -AM25) -> 303.62783 | AQ25: =AQ24+250 -> 4500 | AR25: =PMT(FinanceIt/12, 180, -AQ25) -> 56.906291 | AW25: =AW24+250 -> 14250 | AX25: =PMT(FinanceIt/12, 240, -AW25) -> 166.84803 | AY25: =AY24+250 -> 21500 | AZ25: =PMT(FinanceIt/12, 240, -AY25) -> 251.73563
C26: =C25+250 -> 9500 | D26: =PMT(bnc_7500/12, 120, -C26) -> 130.27168 | E26: =PMT(bnc_7500/26, 120/12*26, -C26) -> 60.044568 | F26: =PMT(bnc_7500/52, 120/12*52, -C26) -> 30.00495 | J26: =J25+250 -> 14750 | K26: =PMT(bnc_10000/12, 120, -J26) -> 202.26393 | L26: =PMT(bnc_10000/26, 120/12*26, -J26) -> 93.227092 | M26: =PMT(bnc_10000/52, 120/12*52, -J26) -> 46.586633 | P26: =P25+250 -> 4750 | Q26: =PMT(0.0499/12, 36, -P26) -> 142.34044 | R26: =R25+250 -> 12000 | S26: =PMT(0.0499/12, 36, -R26) -> 359.59689 | V26: =V25+250 -> 4750 | W26: =PMT(0.0599/12, 48, -V26) -> 111.53211 | X26: =X25+250 -> 12000 | Y26: =PMT(0.0599/12, 48, -X26) -> 281.76533 | AC26: =AC25+250 -> 4750 | AD26: =PMT(0.0899/12, 60, -AC26) -> 98.579136 | AE26: =AE25+250 -> 12000 | AF26: =PMT(0.0899/12, 60, -AE26) -> 249.04203 | AJ26: =AJ25+250 -> 4750 | AK26: =PMT(0.1099/12, 36, -AJ26) -> 155.48641 | AL26: =PMT(0.1099/12, 48, -AJ26) -> 122.74317 | AM26: =AM25+250 -> 12000 | AN26: =PMT(0.1099/12, 36, -AM26) -> 392.80778 | AO26: =PMT(0.1099/12, 48, -AM26) -> 310.088 | AQ26: =AQ25+250 -> 4750 | AR26: =PMT(FinanceIt/12, 180, -AQ26) -> 60.067751 | AW26: =AW25+250 -> 14500 | AX26: =PMT(FinanceIt/12, 240, -AW26) -> 169.77519 | AY26: =AY25+250 -> 21750 | AZ26: =PMT(FinanceIt/12, 240, -AY26) -> 254.66279
C27: =C26+250 -> 9750 | D27: =PMT(bnc_7500/12, 120, -C27) -> 133.69988 | E27: =PMT(bnc_7500/26, 120/12*26, -C27) -> 61.624688 | F27: =PMT(bnc_7500/52, 120/12*52, -C27) -> 30.794554 | I27: 180 MOIS @ 11.49% | J27: =J26+250 -> 15000 | K27: =PMT(bnc_15000/12, 180, -J27) -> 175.13312 | L27: =PMT(bnc_15000/26, 180/12*26, -J27) -> 80.752862 | M27: =PMT(bnc_15000/52, 180/12*52, -J27) -> 40.359752 | P27: =P26+250 -> 5000 | Q27: =PMT(0.0499/12, 36, -P27) -> 149.83204 | R27: =R26+250 -> 12250 | S27: =PMT(0.0499/12, 36, -R27) -> 367.08849 | V27: =V26+250 -> 5000 | W27: =PMT(0.0599/12, 48, -V27) -> 117.40222 | X27: =X26+250 -> 12250 | Y27: =PMT(0.0599/12, 48, -X27) -> 287.63545 | AC27: =AC26+250 -> 5000 | AD27: =PMT(0.0899/12, 60, -AC27) -> 103.76751 | AE27: =AE26+250 -> 12250 | AF27: =PMT(0.0899/12, 60, -AE27) -> 254.2304 | AJ27: =AJ26+250 -> 5000 | AK27: =PMT(0.1099/12, 36, -AJ27) -> 163.66991 | AL27: =PMT(0.1099/12, 48, -AJ27) -> 129.20333 | AM27: =AM26+250 -> 12250 | AN27: =PMT(0.1099/12, 36, -AM27) -> 400.99128 | AO27: =PMT(0.1099/12, 48, -AM27) -> 316.54817 | AQ27: =AQ26+250 -> 5000 | AR27: =PMT(FinanceIt/12, 180, -AQ27) -> 63.229212 | AW27: =AW26+250 -> 14750 | AX27: =PMT(FinanceIt/12, 240, -AW27) -> 172.70235 | AY27: =AY26+250 -> 22000 | AZ27: =PMT(FinanceIt/12, 240, -AY27) -> 257.58995
C28: =C27+250 -> 10000 | D28: =PMT(bnc_7500/12, 120, -C28) -> 137.12809 | E28: =PMT(bnc_7500/26, 120/12*26, -C28) -> 63.204808 | F28: =PMT(bnc_7500/52, 120/12*52, -C28) -> 31.584158 | J28: =J27+250 -> 15250 | K28: =PMT(bnc_15000/12, 180, -J28) -> 178.05201 | L28: =PMT(bnc_15000/26, 180/12*26, -J28) -> 82.098743 | M28: =PMT(bnc_15000/52, 180/12*52, -J28) -> 41.032414 | P28: =P27+250 -> 5250 | Q28: =PMT(0.0499/12, 36, -P28) -> 157.32364 | R28: =R27+250 -> 12500 | S28: =PMT(0.0499/12, 36, -R28) -> 374.58009 | V28: =V27+250 -> 5250 | W28: =PMT(0.0599/12, 48, -V28) -> 123.27233 | X28: =X27+250 -> 12500 | Y28: =PMT(0.0599/12, 48, -X28) -> 293.50556 | AC28: =AC27+250 -> 5250 | AD28: =PMT(0.0899/12, 60, -AC28) -> 108.95589 | AE28: =AE27+250 -> 12500 | AF28: =PMT(0.0899/12, 60, -AE28) -> 259.41878 | AJ28: =AJ27+250 -> 5250 | AK28: =PMT(0.1099/12, 36, -AJ28) -> 171.8534 | AL28: =PMT(0.1099/12, 48, -AJ28) -> 135.6635 | AM28: =AM27+250 -> 12500 | AN28: =PMT(0.1099/12, 36, -AM28) -> 409.17477 | AO28: =PMT(0.1099/12, 48, -AM28) -> 323.00833 | AQ28: =AQ27+250 -> 5250 | AR28: =PMT(FinanceIt/12, 180, -AQ28) -> 66.390673 | AW28: =AW27+250 -> 15000 | AX28: =PMT(FinanceIt/12, 240, -AW28) -> 175.62951 | AY28: =AY27+250 -> 22250 | AZ28: =PMT(FinanceIt/12, 240, -AY28) -> 260.5171
J29: =J28+250 -> 15500 | K29: =PMT(bnc_15000/12, 180, -J29) -> 180.97089 | L29: =PMT(bnc_15000/26, 180/12*26, -J29) -> 83.444624 | M29: =PMT(bnc_15000/52, 180/12*52, -J29) -> 41.705077 | P29: =P28+250 -> 5500 | Q29: =PMT(0.0499/12, 36, -P29) -> 164.81524 | R29: =R28+250 -> 12750 | S29: =PMT(0.0499/12, 36, -R29) -> 382.0717 | V29: =V28+250 -> 5500 | W29: =PMT(0.0599/12, 48, -V29) -> 129.14244 | X29: =X28+250 -> 12750 | Y29: =PMT(0.0599/12, 48, -X29) -> 299.37567 | AC29: =AC28+250 -> 5500 | AD29: =PMT(0.0899/12, 60, -AC29) -> 114.14426 | AE29: =AE28+250 -> 12750 | AF29: =PMT(0.0899/12, 60, -AE29) -> 264.60715 | AJ29: =AJ28+250 -> 5500 | AK29: =PMT(0.1099/12, 36, -AJ29) -> 180.0369 | AL29: =PMT(0.1099/12, 48, -AJ29) -> 142.12367 | AM29: =AM28+250 -> 12750 | AN29: =PMT(0.1099/12, 36, -AM29) -> 417.35827 | AO29: =PMT(0.1099/12, 48, -AM29) -> 329.4685 | AQ29: =AQ28+250 -> 5500 | AR29: =PMT(FinanceIt/12, 180, -AQ29) -> 69.552133 | AW29: =AW28+250 -> 15250 | AX29: =PMT(FinanceIt/12, 240, -AW29) -> 178.55667 | AY29: =AY28+250 -> 22500 | AZ29: =PMT(FinanceIt/12, 240, -AY29) -> 263.44426
J30: =J29+250 -> 15750 | K30: =PMT(bnc_15000/12, 180, -J30) -> 183.88978 | L30: =PMT(bnc_15000/26, 180/12*26, -J30) -> 84.790505 | M30: =PMT(bnc_15000/52, 180/12*52, -J30) -> 42.377739 | P30: =P29+250 -> 5750 | Q30: =PMT(0.0499/12, 36, -P30) -> 172.30684 | R30: =R29+250 -> 13000 | S30: =PMT(0.0499/12, 36, -R30) -> 389.5633 | V30: =V29+250 -> 5750 | W30: =PMT(0.0599/12, 48, -V30) -> 135.01256 | X30: =X29+250 -> 13000 | Y30: =PMT(0.0599/12, 48, -X30) -> 305.24578 | AC30: =AC29+250 -> 5750 | AD30: =PMT(0.0899/12, 60, -AC30) -> 119.33264 | AE30: =AE29+250 -> 13000 | AF30: =PMT(0.0899/12, 60, -AE30) -> 269.79553 | AJ30: =AJ29+250 -> 5750 | AK30: =PMT(0.1099/12, 36, -AJ30) -> 188.22039 | AL30: =PMT(0.1099/12, 48, -AJ30) -> 148.58383 | AM30: =AM29+250 -> 13000 | AN30: =PMT(0.1099/12, 36, -AM30) -> 425.54176 | AO30: =PMT(0.1099/12, 48, -AM30) -> 335.92867 | AQ30: =AQ29+250 -> 5750 | AR30: =PMT(FinanceIt/12, 180, -AQ30) -> 72.713594 | AW30: =AW29+250 -> 15500 | AX30: =PMT(FinanceIt/12, 240, -AW30) -> 181.48382 | AY30: =AY29+250 -> 22750 | AZ30: =PMT(FinanceIt/12, 240, -AY30) -> 266.37142
J31: =J30+250 -> 16000 | K31: =PMT(bnc_15000/12, 180, -J31) -> 186.80866 | L31: =PMT(bnc_15000/26, 180/12*26, -J31) -> 86.136386 | M31: =PMT(bnc_15000/52, 180/12*52, -J31) -> 43.050402 | P31: =P30+250 -> 6000 | Q31: =PMT(0.0499/12, 36, -P31) -> 179.79845 | R31: =R30+250 -> 13250 | S31: =PMT(0.0499/12, 36, -R31) -> 397.0549 | V31: =V30+250 -> 6000 | W31: =PMT(0.0599/12, 48, -V31) -> 140.88267 | X31: =X30+250 -> 13250 | Y31: =PMT(0.0599/12, 48, -X31) -> 311.11589 | AC31: =AC30+250 -> 6000 | AD31: =PMT(0.0899/12, 60, -AC31) -> 124.52101 | AE31: =AE30+250 -> 13250 | AF31: =PMT(0.0899/12, 60, -AE31) -> 274.9839 | AJ31: =AJ30+250 -> 6000 | AK31: =PMT(0.1099/12, 36, -AJ31) -> 196.40389 | AL31: =PMT(0.1099/12, 48, -AJ31) -> 155.044 | AM31: =AM30+250 -> 13250 | AN31: =PMT(0.1099/12, 36, -AM31) -> 433.72526 | AO31: =PMT(0.1099/12, 48, -AM31) -> 342.38883 | AQ31: =AQ30+250 -> 6000 | AR31: =PMT(FinanceIt/12, 180, -AQ31) -> 75.875054 | AW31: =AW30+250 -> 15750 | AX31: =PMT(FinanceIt/12, 240, -AW31) -> 184.41098 | AY31: =AY30+250 -> 23000 | AZ31: =PMT(FinanceIt/12, 240, -AY31) -> 269.29858
J32: =J31+250 -> 16250 | K32: =PMT(bnc_15000/12, 180, -J32) -> 189.72755 | L32: =PMT(bnc_15000/26, 180/12*26, -J32) -> 87.482267 | M32: =PMT(bnc_15000/52, 180/12*52, -J32) -> 43.723064 | P32: =P31+250 -> 6250 | Q32: =PMT(0.0499/12, 36, -P32) -> 187.29005 | R32: =R31+250 -> 13500 | S32: =PMT(0.0499/12, 36, -R32) -> 404.5465 | V32: =V31+250 -> 6250 | W32: =PMT(0.0599/12, 48, -V32) -> 146.75278 | X32: =X31+250 -> 13500 | Y32: =PMT(0.0599/12, 48, -X32) -> 316.986 | AC32: =AC31+250 -> 6250 | AD32: =PMT(0.0899/12, 60, -AC32) -> 129.70939 | AE32: =AE31+250 -> 13500 | AF32: =PMT(0.0899/12, 60, -AE32) -> 280.17228 | AJ32: =AJ31+250 -> 6250 | AK32: =PMT(0.1099/12, 36, -AJ32) -> 204.58739 | AL32: =PMT(0.1099/12, 48, -AJ32) -> 161.50417 | AM32: =AM31+250 -> 13500 | AN32: =PMT(0.1099/12, 36, -AM32) -> 441.90875 | AO32: =PMT(0.1099/12, 48, -AM32) -> 348.849 | AQ32: =AQ31+250 -> 6250 | AR32: =PMT(FinanceIt/12, 180, -AQ32) -> 79.036515 | AW32: =AW31+250 -> 16000 | AX32: =PMT(FinanceIt/12, 240, -AW32) -> 187.33814 | AY32: =AY31+250 -> 23250 | AZ32: =PMT(FinanceIt/12, 240, -AY32) -> 272.22574
J33: =J32+250 -> 16500 | K33: =PMT(bnc_15000/12, 180, -J33) -> 192.64643 | L33: =PMT(bnc_15000/26, 180/12*26, -J33) -> 88.828148 | M33: =PMT(bnc_15000/52, 180/12*52, -J33) -> 44.395727 | P33: =P32+250 -> 6500 | Q33: =PMT(0.0499/12, 36, -P33) -> 194.78165 | R33: =R32+250 -> 13750 | S33: =PMT(0.0499/12, 36, -R33) -> 412.0381 | V33: =V32+250 -> 6500 | W33: =PMT(0.0599/12, 48, -V33) -> 152.62289 | X33: =X32+250 -> 13750 | Y33: =PMT(0.0599/12, 48, -X33) -> 322.85611 | AC33: =AC32+250 -> 6500 | AD33: =PMT(0.0899/12, 60, -AC33) -> 134.89776 | AE33: =AE32+250 -> 13750 | AF33: =PMT(0.0899/12, 60, -AE33) -> 285.36066 | AJ33: =AJ32+250 -> 6500 | AK33: =PMT(0.1099/12, 36, -AJ33) -> 212.77088 | AL33: =PMT(0.1099/12, 48, -AJ33) -> 167.96433 | AM33: =AM32+250 -> 13750 | AN33: =PMT(0.1099/12, 36, -AM33) -> 450.09225 | AO33: =PMT(0.1099/12, 48, -AM33) -> 355.30917 | AQ33: =AQ32+250 -> 6500 | AR33: =PMT(FinanceIt/12, 180, -AQ33) -> 82.197976 | AW33: =AW32+250 -> 16250 | AX33: =PMT(FinanceIt/12, 240, -AW33) -> 190.2653 | AY33: =AY32+250 -> 23500 | AZ33: =PMT(FinanceIt/12, 240, -AY33) -> 275.1529
J34: =J33+250 -> 16750 | K34: =PMT(bnc_15000/12, 180, -J34) -> 195.56532 | L34: =PMT(bnc_15000/26, 180/12*26, -J34) -> 90.174029 | M34: =PMT(bnc_15000/52, 180/12*52, -J34) -> 45.068389 | P34: =P33+250 -> 6750 | Q34: =PMT(0.0499/12, 36, -P34) -> 202.27325 | R34: =R33+250 -> 14000 | S34: =PMT(0.0499/12, 36, -R34) -> 419.52971 | V34: =V33+250 -> 6750 | W34: =PMT(0.0599/12, 48, -V34) -> 158.493 | X34: =X33+250 -> 14000 | Y34: =PMT(0.0599/12, 48, -X34) -> 328.72622 | AC34: =AC33+250 -> 6750 | AD34: =PMT(0.0899/12, 60, -AC34) -> 140.08614 | AE34: =AE33+250 -> 14000 | AF34: =PMT(0.0899/12, 60, -AE34) -> 290.54903 | AJ34: =AJ33+250 -> 6750 | AK34: =PMT(0.1099/12, 36, -AJ34) -> 220.95438 | AL34: =PMT(0.1099/12, 48, -AJ34) -> 174.4245 | AM34: =AM33+250 -> 14000 | AN34: =PMT(0.1099/12, 36, -AM34) -> 458.27574 | AO34: =PMT(0.1099/12, 48, -AM34) -> 361.76933 | AQ34: =AQ33+250 -> 6750 | AR34: =PMT(FinanceIt/12, 180, -AQ34) -> 85.359436 | AW34: =AW33+250 -> 16500 | AX34: =PMT(FinanceIt/12, 240, -AW34) -> 193.19246 | AY34: =AY33+250 -> 23750 | AZ34: =PMT(FinanceIt/12, 240, -AY34) -> 278.08005
J35: =J34+250 -> 17000 | K35: =PMT(bnc_15000/12, 180, -J35) -> 198.4842 | L35: =PMT(bnc_15000/26, 180/12*26, -J35) -> 91.51991 | M35: =PMT(bnc_15000/52, 180/12*52, -J35) -> 45.741052 | P35: =P34+250 -> 7000 | Q35: =PMT(0.0499/12, 36, -P35) -> 209.76485 | R35: =R34+250 -> 14250 | S35: =PMT(0.0499/12, 36, -R35) -> 427.02131 | V35: =V34+250 -> 7000 | W35: =PMT(0.0599/12, 48, -V35) -> 164.36311 | X35: =X34+250 -> 14250 | Y35: =PMT(0.0599/12, 48, -X35) -> 334.59633 | AC35: =AC34+250 -> 7000 | AD35: =PMT(0.0899/12, 60, -AC35) -> 145.27452 | AE35: =AE34+250 -> 14250 | AF35: =PMT(0.0899/12, 60, -AE35) -> 295.73741 | AJ35: =AJ34+250 -> 7000 | AK35: =PMT(0.1099/12, 36, -AJ35) -> 229.13787 | AL35: =PMT(0.1099/12, 48, -AJ35) -> 180.88467 | AM35: =AM34+250 -> 14250 | AN35: =PMT(0.1099/12, 36, -AM35) -> 466.45924 | AO35: =PMT(0.1099/12, 48, -AM35) -> 368.2295 | AQ35: =AQ34+250 -> 7000 | AR35: =PMT(FinanceIt/12, 180, -AQ35) -> 88.520897 | AW35: =AW34+250 -> 16750 | AX35: =PMT(FinanceIt/12, 240, -AW35) -> 196.11962 | AY35: =AY34+250 -> 24000 | AZ35: =PMT(FinanceIt/12, 240, -AY35) -> 281.00721
J36: + 1,000$ | K36: =PMT(bnc_15000/12, 180, -1000) -> 11.675541 | L36: =PMT(bnc_15000/26, 180/12*26, -1000) -> 5.3835241 | M36: =PMT(bnc_15000/52, 180/12*52, -1000) -> 2.6906501 | P36: =P35+250 -> 7250 | Q36: =PMT(0.0499/12, 36, -P36) -> 217.25645 | R36: =R35+250 -> 14500 | S36: =PMT(0.0499/12, 36, -R36) -> 434.51291 | V36: =V35+250 -> 7250 | W36: =PMT(0.0599/12, 48, -V36) -> 170.23322 | X36: =X35+250 -> 14500 | Y36: =PMT(0.0599/12, 48, -X36) -> 340.46645 | AC36: =AC35+250 -> 7250 | AD36: =PMT(0.0899/12, 60, -AC36) -> 150.46289 | AE36: =AE35+250 -> 14500 | AF36: =PMT(0.0899/12, 60, -AE36) -> 300.92578 | AJ36: =AJ35+250 -> 7250 | AK36: =PMT(0.1099/12, 36, -AJ36) -> 237.32137 | AL36: =PMT(0.1099/12, 48, -AJ36) -> 187.34483 | AM36: =AM35+250 -> 14500 | AN36: =PMT(0.1099/12, 36, -AM36) -> 474.64273 | AO36: =PMT(0.1099/12, 48, -AM36) -> 374.68967 | AQ36: =AQ35+250 -> 7250 | AR36: =PMT(FinanceIt/12, 180, -AQ36) -> 91.682357 | AW36: =AW35+250 -> 17000 | AX36: =PMT(FinanceIt/12, 240, -AW36) -> 199.04678 | AY36: + 1000$ | AZ36: =PMT(FinanceIt/12, 240, -1000) -> 11.708634

Sheet Calculatrice
A1: Options de Financement
A2: =NOW() -> 45786.48
A8: Montant d'achat | B8: 5000
A9: TPS | B9: =ROUND(B8*0.05,2) -> 250
A10: TVQ | B10: =ROUND(SUM(B8:B9)*0.095,2) -> 498.75
A11: Montant a Financer | B11: =SUM(B8:B10) -> 5748.75
A16: Option de Financement | B16: Plan | C16: Terme | D16: Fréquence | E16: Taux Annuel | F16: Paiement | G16: Solde a terme | H16: Commerçant | I16: Coût Commerçant | J16: Coût Conso
A18: Fairstone
A19: 12 mois pas de Paiement/ Pas d'intéret(CAN) | B19: 12120 | C19: 12 | D19: Aucun | E19: 0 | G19: =MontantFinancement -> 5748.75 | H19: 0.0529 | I19: =MontantFinancement*H19 -> 304.10888 | J19: =(G19+(F19*C19))-MontantFinancement -> 0
A20: 24 mois pas de Paiement/ Pas d'intéret(CAN) | B20: 12240 | C20: 24 | D20: Aucun | E20: 0 | G20: =MontantFinancement -> 5748.75 | H20: 0.0629 | I20: =MontantFinancement*H20 -> 361.59637 | J20: =(G20+(F20*C20))-MontantFinancement -> 0
A21: 3 Mois Option Comptant | B21: 13030 | C21: 3 | D21: Mensuel | E21: 0 | F21: =MontantFinancement*0.05 -> 287.4375 | G21: =MontantFinancement-(F21*C21) -> 4886.4375 | H21: 0.0149 | I21: =MontantFinancement*H21 -> 85.656375 | J21: =(G21+(F21*C21))-MontantFinancement -> 0
A22: 6 Mois Option Comptant | B22: 13060 | C22: 6 | D22: Mensuel | E22: 0 | F22: =MontantFinancement*0.05 -> 287.4375 | G22: =MontantFinancement-(F22*C22) -> 4024.125 | H22: 0.0199 | I22: =MontantFinancement*H22 -> 114.40013 | J22: =(G22+(F22*C22))-MontantFinancement -> 0
A23: 12 Mois Option Comptant | B23: 13120 | C23: 12 | D23: Mensuel | E23: 0 | F23: =MontantFinancement*0.05 -> 287.4375 | G23: =MontantFinancement-(F23*C23) -> 2299.5 | H23: 0.0299 | I23: =MontantFinancement*H23 -> 171.88762 | J23: =(G23+(F23*C23))-MontantFinancement -> 0
A24: 24 Mois Option Comptant | B24: 13240 | C24: 24 | D24: Mensuel | E24: 0 | F24: =MontantFinancement*0.05 -> 287.4375 | H24: 0.0399 | I24: =MontantFinancement*H24 -> 229.37512
A25: 36 Payments égaux sans intérêt | B25: 16360 | C25: 36 | D25: Mensuel | E25: 0 | F25: =MontantFinancement/C25 -> 159.6875 | G25: =MontantFinancement-(F25*C25) -> 0 | H25: 0.1349 | I25: =MontantFinancement*H25 -> 775.50637 | J25: =(G25+(F25*C25))-MontantFinancement -> 0
A26: 36 Payments égaux avec intérêt | B26: 36369 | C26: 36 | D26: Mensuel | E26: 0.0499 | F26: =PMT(E26/12, C26, -MontantFinancement) -> 172.26939 | G26: 0 | H26: 0.0599 | I26: =MontantFinancement*H26 -> 344.35012 | J26: =(G26+(F26*C26))-MontantFinancement -> 452.94787
A27: 36 Payments égaux avec intérêt | B27: 18363 | C27: 36 | D27: Mensuel | E27: 0.1099 | F27: =PMT(E27/12, C27, -MontantFinancement) -> 188.17948 | G27: 0 | H27: 0.0299 | I27: =MontantFinancement*H27 -> 171.88762 | J27: =(G27+(F27*C27))-MontantFinancement -> 1025.7112
A28: 48 Payments égaux avec intérêt | B28: 36485 | C28: 48 | D28: Mensuel | E28: 0.0599 | F28: =PMT(E28/12, C28, -MontantFinancement) -> 134.98321 | G28: 0 | H28: 0.0699 | I28: =MontantFinancement*H28 -> 401.83763 | J28: =(G28+(F28*C28))-MontantFinancement -> 730.44387
A29: 48 Payments égaux avec intérêt | B29: 18483 | C29: 48 | D29: Mensuel | E29: 0.1099 | F29: =PMT(E29/12, C29, -MontantFinancement) -> 148.55153 | G29: 0 | H29: 0.0309 | I29: =MontantFinancement*H29 -> 177.63638 | J29: =(G29+(F29*C29))-MontantFinancement -> 1381.7235
A30: 60 Payments égaux avec intérêt | B30: 36602 | C30: 60 | D30: Mensuel | E30: 0.0899 | F30: =PMT(E30/12, C30, -MontantFinancement) -> 119.3067 | G30: 0 | H30: 0.0649 | I30: =MontantFinancement*H30 -> 373.09387 | J30: =(G30+(F30*C30))-MontantFinancement -> 1409.6518
A32: BNC
A33: Taux Fixe paiement Mensuel | B33: N/A | C33: =_xlfn.XLOOKUP(MontantFinancement, Taux!$A$4:$A$8, Taux!$C$4:$C$8,,-1) -> 120 | D33: Mensuel | E33: =_xlfn.XLOOKUP(MontantFinancement,Taux!$A$4:$A$8,Taux!$D$4:$D$8,,-1) -> 0.1139 | F33: =PMT(E33/12, C33, -MontantFinancement) -> 80.463447 | J33: =(G33+(F33*C33))-MontantFinancement -> 3906.8636
A34: Taux Fixe paiement aux 2 semaines | B34: N/A | C34: =_xlfn.XLOOKUP(MontantFinancement, Taux!$A$4:$A$8, Taux!$C$4:$C$8,,-1) -> 120 | D34: 2 Semaines | E34: =_xlfn.XLOOKUP(MontantFinancement,Taux!$A$4:$A$8,Taux!$D$4:$D$8,,-1) -> 0.1139 | F34: =PMT(E34/26, C34/12*26, -MontantFinancement) -> 37.086284
A35: Taux Fixe paiement hebdomadaire | B35: N/A | C35: =_xlfn.XLOOKUP(MontantFinancement, Taux!$A$4:$A$8, Taux!$C$4:$C$8,,-1) -> 120 | D35: Hebdomadaire | E35: =_xlfn.XLOOKUP(MontantFinancement,Taux!$A$4:$A$8,Taux!$D$4:$D$8,,-1) -> 0.1139 | F35: =PMT(E35/52, C35/12*52, -MontantFinancement) -> 18.532271
A37: Finance It
A38: Taux Fixe | B38: N/A | C38: =_xlfn.XLOOKUP(MontantFinancement, Taux!$A$4:$A$8, Taux!$E$4:$E$8,,-1) -> 180 | D38: Mensuel | E38: 0.1299 | F38: =PMT(E38/12, C38, -MontantFinancement) -> 72.697787 | J38: =(G38+(F38*C38))-MontantFinancement -> 7336.8516

Sheet Taux
C2: BNC | E2: FinanceIt
A3: From | B3: To | C3: Terme | D3: Taux | E3: Terme | F3: Taux
A4: 0 | B4: 5000 | C4: 0 | D4: 0 | E4: 180 | F4: 0.1299
A5: 5000 | B5: 7499 | C5: 120 | D5: 0.1139 | E5: 180 | F5: 0.1299
A6: 7500 | B6: 9999 | C6: 120 | D6: 0.1089 | E6: 180 | F6: 0.1299
A7: 10000 | B7: 14999 | C7: 120 | D7: 0.1089 | E7: 240 | F7: 0.1299
A8: 15000 | C8: 180 | D8: 0.1149 | E8: 240 | F8: 0.1299
